fakelion.py
setup.py
fakelion.egg-info/PKG-INFO
fakelion.egg-info/SOURCES.txt
fakelion.egg-info/dependency_links.txt
fakelion.egg-info/not-zip-safe
fakelion.egg-info/top_level.txt