Metadata-Version: 1.1
Name: fakelion
Version: 1.0.0a2
Summary: Script to produce fake translations for .po files
Home-page: https://launchpad.net/fakelion
Author: Mike C. Fletcher
Author-email: mcfletch@vrplumber.com
License: BSD
Platform: UNKNOWN
Requires: polib
